{"nodes": [{"id": "c_proj_svadba_app_bot_handlers_invoices_py", "label": "invoices.py", "file_type": "code", "source_file": "app/bot/handlers/invoices.py", "source_location": "L1"}, {"id": "handlers_invoices_invoicestates", "label": "InvoiceStates", "file_type": "code", "source_file": "app/bot/handlers/invoices.py", "source_location": "L18"}, {"id": "statesgroup", "label": "StatesGroup", "file_type": "code", "source_file": "", "source_location": ""}, {"id": "handlers_invoices_cmd_payments", "label": "cmd_payments()", "file_type": "code", "source_file": "app/bot/handlers/invoices.py", "source_location": "L24"}, {"id": "message", "label": "Message", "file_type": "code", "source_file": "", "source_location": "", "origin_file": "C:\\PROJ\\SVADBA\\app\\bot\\handlers\\invoices.py"}, {"id": "handlers_invoices_menu_invoices", "label": "menu_invoices()", "file_type": "code", "source_file": "app/bot/handlers/invoices.py", "source_location": "L44"}, {"id": "callbackquery", "label": "CallbackQuery", "file_type": "code", "source_file": "", "source_location": "", "origin_file": "C:\\PROJ\\SVADBA\\app\\bot\\handlers\\invoices.py"}, {"id": "handlers_invoices_invoice_create_start", "label": "invoice_create_start()", "file_type": "code", "source_file": "app/bot/handlers/invoices.py", "source_location": "L64"}, {"id": "fsmcontext", "label": "FSMContext", "file_type": "code", "source_file": "", "source_location": "", "origin_file": "C:\\PROJ\\SVADBA\\app\\bot\\handlers\\invoices.py"}, {"id": "handlers_invoices_process_amount", "label": "process_amount()", "file_type": "code", "source_file": "app/bot/handlers/invoices.py", "source_location": "L73"}, {"id": "handlers_invoices_process_description", "label": "process_description()", "file_type": "code", "source_file": "app/bot/handlers/invoices.py", "source_location": "L88"}], "edges": [{"source": "c_proj_svadba_app_bot_handlers_invoices_py", "target": "decimal", "relation": "imports_from", "context": "import", "confidence": "EXTRACTED", "source_file": "app/bot/handlers/invoices.py", "source_location": "L1", "weight": 1.0}, {"source": "c_proj_svadba_app_bot_handlers_invoices_py", "target": "aiogram", "relation": "imports_from", "context": "import", "confidence": "EXTRACTED", "source_file": "app/bot/handlers/invoices.py", "source_location": "L3", "weight": 1.0}, {"source": "c_proj_svadba_app_bot_handlers_invoices_py", "target": "aiogram_filters", "relation": "imports_from", "context": "import", "confidence": "EXTRACTED", "source_file": "app/bot/handlers/invoices.py", "source_location": "L4", "weight": 1.0}, {"source": "c_proj_svadba_app_bot_handlers_invoices_py", "target": "aiogram_fsm_context", "relation": "imports_from", "context": "import", "confidence": "EXTRACTED", "source_file": "app/bot/handlers/invoices.py", "source_location": "L5", "weight": 1.0}, {"source": "c_proj_svadba_app_bot_handlers_invoices_py", "target": "aiogram_fsm_state", "relation": "imports_from", "context": "import", "confidence": "EXTRACTED", "source_file": "app/bot/handlers/invoices.py", "source_location": "L6", "weight": 1.0}, {"source": "c_proj_svadba_app_bot_handlers_invoices_py", "target": "aiogram_types", "relation": "imports_from", "context": "import", "confidence": "EXTRACTED", "source_file": "app/bot/handlers/invoices.py", "source_location": "L7", "weight": 1.0}, {"source": "c_proj_svadba_app_bot_handlers_invoices_py", "target": "sqlalchemy", "relation": "imports_from", "context": "import", "confidence": "EXTRACTED", "source_file": "app/bot/handlers/invoices.py", "source_location": "L8", "weight": 1.0}, {"source": "c_proj_svadba_app_bot_handlers_invoices_py", "target": "app_database", "relation": "imports_from", "context": "import", "confidence": "EXTRACTED", "source_file": "app/bot/handlers/invoices.py", "source_location": "L10", "weight": 1.0}, {"source": "c_proj_svadba_app_bot_handlers_invoices_py", "target": "app_models_invoice", "relation": "imports_from", "context": "import", "confidence": "EXTRACTED", "source_file": "app/bot/handlers/invoices.py", "source_location": "L11", "weight": 1.0}, {"source": "c_proj_svadba_app_bot_handlers_invoices_py", "target": "app_services_client_service", "relation": "imports_from", "context": "import", "confidence": "EXTRACTED", "source_file": "app/bot/handlers/invoices.py", "source_location": "L12", "weight": 1.0}, {"source": "c_proj_svadba_app_bot_handlers_invoices_py", "target": "app_services_payment_service", "relation": "imports_from", "context": "import", "confidence": "EXTRACTED", "source_file": "app/bot/handlers/invoices.py", "source_location": "L13", "weight": 1.0}, {"source": "c_proj_svadba_app_bot_handlers_invoices_py", "target": "handlers_invoices_invoicestates", "relation": "contains", "confidence": "EXTRACTED", "source_file": "app/bot/handlers/invoices.py", "source_location": "L18", "weight": 1.0}, {"source": "handlers_invoices_invoicestates", "target": "statesgroup", "relation": "inherits", "confidence": "EXTRACTED", "source_file": "app/bot/handlers/invoices.py", "source_location": "L18", "weight": 1.0}, {"source": "c_proj_svadba_app_bot_handlers_invoices_py", "target": "handlers_invoices_cmd_payments", "relation": "contains", "confidence": "EXTRACTED", "source_file": "app/bot/handlers/invoices.py", "source_location": "L24", "weight": 1.0}, {"source": "handlers_invoices_cmd_payments", "target": "message", "relation": "references", "context": "parameter_type", "confidence": "EXTRACTED", "source_file": "app/bot/handlers/invoices.py", "source_location": "L24", "weight": 1.0}, {"source": "c_proj_svadba_app_bot_handlers_invoices_py", "target": "handlers_invoices_menu_invoices", "relation": "contains", "confidence": "EXTRACTED", "source_file": "app/bot/handlers/invoices.py", "source_location": "L44", "weight": 1.0}, {"source": "handlers_invoices_menu_invoices", "target": "callbackquery", "relation": "references", "context": "parameter_type", "confidence": "EXTRACTED", "source_file": "app/bot/handlers/invoices.py", "source_location": "L44", "weight": 1.0}, {"source": "c_proj_svadba_app_bot_handlers_invoices_py", "target": "handlers_invoices_invoice_create_start", "relation": "contains", "confidence": "EXTRACTED", "source_file": "app/bot/handlers/invoices.py", "source_location": "L64", "weight": 1.0}, {"source": "handlers_invoices_invoice_create_start", "target": "callbackquery", "relation": "references", "context": "parameter_type", "confidence": "EXTRACTED", "source_file": "app/bot/handlers/invoices.py", "source_location": "L64", "weight": 1.0}, {"source": "handlers_invoices_invoice_create_start", "target": "fsmcontext", "relation": "references", "context": "parameter_type", "confidence": "EXTRACTED", "source_file": "app/bot/handlers/invoices.py", "source_location": "L64", "weight": 1.0}, {"source": "c_proj_svadba_app_bot_handlers_invoices_py", "target": "handlers_invoices_process_amount", "relation": "contains", "confidence": "EXTRACTED", "source_file": "app/bot/handlers/invoices.py", "source_location": "L73", "weight": 1.0}, {"source": "handlers_invoices_process_amount", "target": "message", "relation": "references", "context": "parameter_type", "confidence": "EXTRACTED", "source_file": "app/bot/handlers/invoices.py", "source_location": "L73", "weight": 1.0}, {"source": "handlers_invoices_process_amount", "target": "fsmcontext", "relation": "references", "context": "parameter_type", "confidence": "EXTRACTED", "source_file": "app/bot/handlers/invoices.py", "source_location": "L73", "weight": 1.0}, {"source": "c_proj_svadba_app_bot_handlers_invoices_py", "target": "handlers_invoices_process_description", "relation": "contains", "confidence": "EXTRACTED", "source_file": "app/bot/handlers/invoices.py", "source_location": "L88", "weight": 1.0}, {"source": "handlers_invoices_process_description", "target": "message", "relation": "references", "context": "parameter_type", "confidence": "EXTRACTED", "source_file": "app/bot/handlers/invoices.py", "source_location": "L88", "weight": 1.0}, {"source": "handlers_invoices_process_description", "target": "fsmcontext", "relation": "references", "context": "parameter_type", "confidence": "EXTRACTED", "source_file": "app/bot/handlers/invoices.py", "source_location": "L88", "weight": 1.0}], "raw_calls": [{"caller_nid": "handlers_invoices_cmd_payments", "callee": "async_session", "is_member_call": false, "source_file": "C:\\PROJ\\SVADBA\\app\\bot\\handlers\\invoices.py", "source_location": "L25", "receiver": null}, {"caller_nid": "handlers_invoices_cmd_payments", "callee": "execute", "is_member_call": true, "source_file": "C:\\PROJ\\SVADBA\\app\\bot\\handlers\\invoices.py", "source_location": "L26", "receiver": "session"}, {"caller_nid": "handlers_invoices_cmd_payments", "callee": "limit", "is_member_call": true, "source_file": "C:\\PROJ\\SVADBA\\app\\bot\\handlers\\invoices.py", "source_location": "L27", "receiver": null}, {"caller_nid": "handlers_invoices_cmd_payments", "callee": "order_by", "is_member_call": true, "source_file": "C:\\PROJ\\SVADBA\\app\\bot\\handlers\\invoices.py", "source_location": "L27", "receiver": null}, {"caller_nid": "handlers_invoices_cmd_payments", "callee": "select", "is_member_call": false, "source_file": "C:\\PROJ\\SVADBA\\app\\bot\\handlers\\invoices.py", "source_location": "L27", "receiver": null}, {"caller_nid": "handlers_invoices_cmd_payments", "callee": "desc", "is_member_call": true, "source_file": "C:\\PROJ\\SVADBA\\app\\bot\\handlers\\invoices.py", "source_location": "L27", "receiver": null}, {"caller_nid": "handlers_invoices_cmd_payments", "callee": "scalars", "is_member_call": true, "source_file": "C:\\PROJ\\SVADBA\\app\\bot\\handlers\\invoices.py", "source_location": "L29", "receiver": "result"}, {"caller_nid": "handlers_invoices_cmd_payments", "callee": "answer", "is_member_call": true, "source_file": "C:\\PROJ\\SVADBA\\app\\bot\\handlers\\invoices.py", "source_location": "L32", "receiver": "message"}, {"caller_nid": "handlers_invoices_cmd_payments", "callee": "get", "is_member_call": true, "source_file": "C:\\PROJ\\SVADBA\\app\\bot\\handlers\\invoices.py", "source_location": "L38", "receiver": "status_icon"}, {"caller_nid": "handlers_invoices_cmd_payments", "callee": "answer", "is_member_call": true, "source_file": "C:\\PROJ\\SVADBA\\app\\bot\\handlers\\invoices.py", "source_location": "L40", "receiver": "message"}, {"caller_nid": "handlers_invoices_menu_invoices", "callee": "async_session", "is_member_call": false, "source_file": "C:\\PROJ\\SVADBA\\app\\bot\\handlers\\invoices.py", "source_location": "L45", "receiver": null}, {"caller_nid": "handlers_invoices_menu_invoices", "callee": "execute", "is_member_call": true, "source_file": "C:\\PROJ\\SVADBA\\app\\bot\\handlers\\invoices.py", "source_location": "L46", "receiver": "session"}, {"caller_nid": "handlers_invoices_menu_invoices", "callee": "limit", "is_member_call": true, "source_file": "C:\\PROJ\\SVADBA\\app\\bot\\handlers\\invoices.py", "source_location": "L47", "receiver": null}, {"caller_nid": "handlers_invoices_menu_invoices", "callee": "order_by", "is_member_call": true, "source_file": "C:\\PROJ\\SVADBA\\app\\bot\\handlers\\invoices.py", "source_location": "L47", "receiver": null}, {"caller_nid": "handlers_invoices_menu_invoices", "callee": "select", "is_member_call": false, "source_file": "C:\\PROJ\\SVADBA\\app\\bot\\handlers\\invoices.py", "source_location": "L47", "receiver": null}, {"caller_nid": "handlers_invoices_menu_invoices", "callee": "desc", "is_member_call": true, "source_file": "C:\\PROJ\\SVADBA\\app\\bot\\handlers\\invoices.py", "source_location": "L47", "receiver": null}, {"caller_nid": "handlers_invoices_menu_invoices", "callee": "scalars", "is_member_call": true, "source_file": "C:\\PROJ\\SVADBA\\app\\bot\\handlers\\invoices.py", "source_location": "L49", "receiver": "result"}, {"caller_nid": "handlers_invoices_menu_invoices", "callee": "edit_text", "is_member_call": true, "source_file": "C:\\PROJ\\SVADBA\\app\\bot\\handlers\\invoices.py", "source_location": "L52", "receiver": null}, {"caller_nid": "handlers_invoices_menu_invoices", "callee": "get", "is_member_call": true, "source_file": "C:\\PROJ\\SVADBA\\app\\bot\\handlers\\invoices.py", "source_location": "L57", "receiver": "status_icon"}, {"caller_nid": "handlers_invoices_menu_invoices", "callee": "edit_text", "is_member_call": true, "source_file": "C:\\PROJ\\SVADBA\\app\\bot\\handlers\\invoices.py", "source_location": "L59", "receiver": null}, {"caller_nid": "handlers_invoices_menu_invoices", "callee": "answer", "is_member_call": true, "source_file": "C:\\PROJ\\SVADBA\\app\\bot\\handlers\\invoices.py", "source_location": "L60", "receiver": "callback"}, {"caller_nid": "handlers_invoices_invoice_create_start", "callee": "split", "is_member_call": true, "source_file": "C:\\PROJ\\SVADBA\\app\\bot\\handlers\\invoices.py", "source_location": "L65", "receiver": null}, {"caller_nid": "handlers_invoices_invoice_create_start", "callee": "update_data", "is_member_call": true, "source_file": "C:\\PROJ\\SVADBA\\app\\bot\\handlers\\invoices.py", "source_location": "L66", "receiver": "state"}, {"caller_nid": "handlers_invoices_invoice_create_start", "callee": "edit_text", "is_member_call": true, "source_file": "C:\\PROJ\\SVADBA\\app\\bot\\handlers\\invoices.py", "source_location": "L67", "receiver": null}, {"caller_nid": "handlers_invoices_invoice_create_start", "callee": "set_state", "is_member_call": true, "source_file": "C:\\PROJ\\SVADBA\\app\\bot\\handlers\\invoices.py", "source_location": "L68", "receiver": "state"}, {"caller_nid": "handlers_invoices_invoice_create_start", "callee": "answer", "is_member_call": true, "source_file": "C:\\PROJ\\SVADBA\\app\\bot\\handlers\\invoices.py", "source_location": "L69", "receiver": "callback"}, {"caller_nid": "handlers_invoices_process_amount", "callee": "Decimal", "is_member_call": false, "source_file": "C:\\PROJ\\SVADBA\\app\\bot\\handlers\\invoices.py", "source_location": "L75", "receiver": null}, {"caller_nid": "handlers_invoices_process_amount", "callee": "strip", "is_member_call": true, "source_file": "C:\\PROJ\\SVADBA\\app\\bot\\handlers\\invoices.py", "source_location": "L75", "receiver": null}, {"caller_nid": "handlers_invoices_process_amount", "callee": "replace", "is_member_call": true, "source_file": "C:\\PROJ\\SVADBA\\app\\bot\\handlers\\invoices.py", "source_location": "L75", "receiver": null}, {"caller_nid": "handlers_invoices_process_amount", "callee": "answer", "is_member_call": true, "source_file": "C:\\PROJ\\SVADBA\\app\\bot\\handlers\\invoices.py", "source_location": "L79", "receiver": "message"}, {"caller_nid": "handlers_invoices_process_amount", "callee": "update_data", "is_member_call": true, "source_file": "C:\\PROJ\\SVADBA\\app\\bot\\handlers\\invoices.py", "source_location": "L82", "receiver": "state"}, {"caller_nid": "handlers_invoices_process_amount", "callee": "answer", "is_member_call": true, "source_file": "C:\\PROJ\\SVADBA\\app\\bot\\handlers\\invoices.py", "source_location": "L83", "receiver": "message"}, {"caller_nid": "handlers_invoices_process_amount", "callee": "set_state", "is_member_call": true, "source_file": "C:\\PROJ\\SVADBA\\app\\bot\\handlers\\invoices.py", "source_location": "L84", "receiver": "state"}, {"caller_nid": "handlers_invoices_process_description", "callee": "get_data", "is_member_call": true, "source_file": "C:\\PROJ\\SVADBA\\app\\bot\\handlers\\invoices.py", "source_location": "L89", "receiver": "state"}, {"caller_nid": "handlers_invoices_process_description", "callee": "Decimal", "is_member_call": false, "source_file": "C:\\PROJ\\SVADBA\\app\\bot\\handlers\\invoices.py", "source_location": "L91", "receiver": null}, {"caller_nid": "handlers_invoices_process_description", "callee": "async_session", "is_member_call": false, "source_file": "C:\\PROJ\\SVADBA\\app\\bot\\handlers\\invoices.py", "source_location": "L94", "receiver": null}, {"caller_nid": "handlers_invoices_process_description", "callee": "get_client_by_id", "is_member_call": false, "source_file": "C:\\PROJ\\SVADBA\\app\\bot\\handlers\\invoices.py", "source_location": "L95", "receiver": null}, {"caller_nid": "handlers_invoices_process_description", "callee": "answer", "is_member_call": true, "source_file": "C:\\PROJ\\SVADBA\\app\\bot\\handlers\\invoices.py", "source_location": "L97", "receiver": "message"}, {"caller_nid": "handlers_invoices_process_description", "callee": "clear", "is_member_call": true, "source_file": "C:\\PROJ\\SVADBA\\app\\bot\\handlers\\invoices.py", "source_location": "L98", "receiver": "state"}, {"caller_nid": "handlers_invoices_process_description", "callee": "create_invoice", "is_member_call": false, "source_file": "C:\\PROJ\\SVADBA\\app\\bot\\handlers\\invoices.py", "source_location": "L101", "receiver": null}, {"caller_nid": "handlers_invoices_process_description", "callee": "answer", "is_member_call": true, "source_file": "C:\\PROJ\\SVADBA\\app\\bot\\handlers\\invoices.py", "source_location": "L102", "receiver": "message"}, {"caller_nid": "handlers_invoices_process_description", "callee": "clear", "is_member_call": true, "source_file": "C:\\PROJ\\SVADBA\\app\\bot\\handlers\\invoices.py", "source_location": "L108", "receiver": "state"}]}